tagnews/__init__.py
tagnews/crimetype/__init__.py
tagnews/crimetype/benchmark.py
tagnews/crimetype/cli.py
tagnews/crimetype/tag.py
tagnews/crimetype/models/binary_stemmed_logistic/__init__.py
tagnews/crimetype/models/binary_stemmed_logistic/model-20250914-193427.pkl
tagnews/crimetype/models/binary_stemmed_logistic/save_model.py
tagnews/crimetype/models/binary_stemmed_logistic/vectorizer-20250914-193427.pkl
tagnews/data/Boundaries - Community Areas (current).geojson
tagnews/data/glove.6B.50d.txt
tagnews/geoloc/__init__.py
tagnews/geoloc/tag.py
tagnews/geoloc/models/lstm/__init__.py
tagnews/geoloc/models/lstm/save_model.py
tagnews/geoloc/models/lstm/saved/weights-01.hdf5
tagnews/geoloc/models/lstm/saved/weights-02.hdf5
tagnews/senteval/__init__.py
tagnews/senteval/eval.py
tagnews/senteval/police_words.py
tagnews/tests/test_crimetype_tag.py
tagnews/tests/test_geocoder.py
tagnews/tests/test_load_data.py
tagnews/utils/__init__.py
tagnews/utils/load_data.py
tagnews/utils/load_vectorizer.py
tagnews/utils/model_helpers.py
tagnews/utils/neighborhoods.py
tagnews/utils/quick_map.py
tagnews/utils/utils.py
tagnews-1.5.0.dist-info/licenses/LICENSE
tagnews-1.5.0.dist-info/METADATA
tagnews-1.5.0.dist-info/WHEEL
tagnews-1.5.0.dist-info/top_level.txt
tagnews-1.5.0.dist-info/RECORD
