Metadata-Version: 2.4
Name: tagnews
Version: 1.5.0
Summary: automatically tag news articles with justice-related categories and extract location information
Author: Kevin Rose, Josh Herzberg, Matt Sweeney
Project-URL: Repository, https://github.com/chicago-justice-project/article-tagging
Requires-Python: >=3.9
License-File: LICENSE
Requires-Dist: google-cloud-language>=2.17.2
Requires-Dist: h5py>=3.14.0
Requires-Dist: keras>=2.15.0
Requires-Dist: nltk>=3.9.1
Requires-Dist: numpy>=1.26.4
Requires-Dist: pandas>=2.3.2
Requires-Dist: requests>=2.32.5
Requires-Dist: scikit-learn>=1.6.1
Requires-Dist: scipy>=1.13.1
Requires-Dist: shapely>=2.0.7
Requires-Dist: tensorflow==2.15.1
Dynamic: license-file
